futuresio/__init__.py
futuresio/futures.py
futuresio-0.1.1.dist-info/LICENSE-APACHE
futuresio-0.1.1.dist-info/LICENSE-MIT
futuresio-0.1.1.dist-info/METADATA
futuresio-0.1.1.dist-info/WHEEL
futuresio-0.1.1.dist-info/top_level.txt
futuresio-0.1.1.dist-info/RECORD
